poppy/__init__.py
poppy/creatures/__init__.py
poppy/creatures/_version.py
poppy/creatures/abstractcreature.py
poppy/creatures/configure.py
poppy/creatures/ik.py
poppy/creatures/poppy_discover.py
poppy/creatures/poppy_sim.py
poppy/creatures/services_launcher.py
poppy/creatures/snap_launcher.py
poppy_creature-1.8.0.dist-info/DESCRIPTION.rst
poppy_creature-1.8.0.dist-info/METADATA
poppy_creature-1.8.0.dist-info/RECORD
poppy_creature-1.8.0.dist-info/WHEEL
poppy_creature-1.8.0.dist-info/entry_points.txt
poppy_creature-1.8.0.dist-info/metadata.json
poppy_creature-1.8.0.dist-info/top_level.txt
