Metadata-Version: 2.0
Name: poppy-creature
Version: 1.8.0
Summary: Abstract Poppy Creature Software Library
Home-page: https://github.com/poppy-project/poppy-creature
Author: Pierre Rouanet, Matthieu Lapeyre
Author-email: pierre.rouanet@gmail.com
License: GNU GENERAL PUBLIC LICENSE Version 3
Platform: UNKNOWN
Requires-Dist: bottle
Requires-Dist: ikpy (>=2.0)
Requires-Dist: pypot (>=2.11.0)
